pafi/__init__.py
pafi/check_dependencies.py
pafi/run_tests.py
pafi/managers/BaseManager.py
pafi/managers/PAFIManager.py
pafi/parsers/BaseParser.py
pafi/parsers/PAFIParser.py
pafi/results/BaseGatherer.py
pafi/results/Gatherer.py
pafi/results/ResultsHolder.py
pafi/results/ResultsProcessor.py
pafi/workers/BaseWorker.py
pafi/workers/LAMMPSWorker.py
pafi/workers/PAFIWorker.py
pafi-0.9.9.1.dist-info/LICENSE
pafi-0.9.9.1.dist-info/METADATA
pafi-0.9.9.1.dist-info/WHEEL
pafi-0.9.9.1.dist-info/entry_points.txt
pafi-0.9.9.1.dist-info/top_level.txt
pafi-0.9.9.1.dist-info/RECORD
