Metadata-Version: 2.1
Name: pafi
Version: 0.9.9.1
Summary: PAFI: A Python package for the evaluation of free energy barriers beyond Harmonic TST using LAMMPS
Author-email: TD Swinburne <thomas.swinburne@cnrs.fr>
License: MIT License
Project-URL: Homepage, https://github.com/tomswinburne/pafi
Project-URL: Documentation, https://github.com/tomswinburne/pafi
Project-URL: Source, https://github.com/tomswinburne/pafi
Classifier: Programming Language :: Python :: 3
Classifier: License :: OSI Approved :: MIT License
Classifier: Operating System :: OS Independent
Requires-Python: >=3.9
License-File: LICENSE
Requires-Dist: numpy>=1.21
Requires-Dist: scipy>=1.7
Requires-Dist: mpi4py>=3.1
Requires-Dist: matplotlib>=3.4
Requires-Dist: pandas>=1.3
Provides-Extra: dev
Requires-Dist: pytest<7.0,>=6.2; extra == "dev"
